psusannx_s3/__init__.py
psusannx_s3/psusannx_s3.py
psusannx_s3-0.0.6.dist-info/METADATA
psusannx_s3-0.0.6.dist-info/WHEEL
psusannx_s3-0.0.6.dist-info/top_level.txt
psusannx_s3-0.0.6.dist-info/RECORD
