Metadata-Version: 2.1
Name: psusannx-s3
Version: 0.0.6
Summary: A package for reading/writing certain file types to the AWS S3 service using boto3.
Author: Jamie O'Brien
Project-URL: Source Code, https://github.com/jamieob63/psusannx_s3.git
Project-URL: Bug Tracker, https://github.com/jamieob63/psusannx_s3.git/issues
Requires-Dist: boto3 (>=1.24.28)
Requires-Dist: pandas (>=1.3.4)
Requires-Dist: tensorflow (>=2.13.0)
